MANIFEST.in
README.rst
setup.cfg
setup.py
django_tastypie_simple_api_doc.egg-info/PKG-INFO
django_tastypie_simple_api_doc.egg-info/SOURCES.txt
django_tastypie_simple_api_doc.egg-info/dependency_links.txt
django_tastypie_simple_api_doc.egg-info/entry_points.txt
django_tastypie_simple_api_doc.egg-info/not-zip-safe
django_tastypie_simple_api_doc.egg-info/requires.txt
django_tastypie_simple_api_doc.egg-info/top_level.txt
tastypie_api_doc/__init__.py
tastypie_api_doc/tests.py
tastypie_api_doc/views.py
tastypie_api_doc/static/tastypie_api_doc/tastypie_api_doc_style.css
tastypie_api_doc/static/tastypie_api_doc/bower_components/jquery/dist/jquery.js
tastypie_api_doc/static/tastypie_api_doc/bower_components/jquery/dist/jquery.min.js
tastypie_api_doc/static/tastypie_api_doc/bower_components/jquery/dist/jquery.slim.js
tastypie_api_doc/static/tastypie_api_doc/bower_components/jquery/dist/jquery.slim.min.js
tastypie_api_doc/static/tastypie_api_doc/bower_components/semantic/dist/semantic.css
tastypie_api_doc/static/tastypie_api_doc/bower_components/semantic/dist/semantic.js
tastypie_api_doc/static/tastypie_api_doc/bower_components/semantic/dist/semantic.min.css
tastypie_api_doc/static/tastypie_api_doc/bower_components/semantic/dist/semantic.min.js
tastypie_api_doc/static/tastypie_api_doc/bower_components/semantic/dist/components/accordion.css
tastypie_api_doc/static/tastypie_api_doc/bower_components/semantic/dist/components/accordion.js
tastypie_api_doc/static/tastypie_api_doc/bower_components/semantic/dist/components/accordion.min.css
tastypie_api_doc/static/tastypie_api_doc/bower_components/semantic/dist/components/accordion.min.js
tastypie_api_doc/static/tastypie_api_doc/bower_components/semantic/dist/components/ad.css
tastypie_api_doc/static/tastypie_api_doc/bower_components/semantic/dist/components/ad.min.css
tastypie_api_doc/static/tastypie_api_doc/bower_components/semantic/dist/components/api.js
tastypie_api_doc/static/tastypie_api_doc/bower_components/semantic/dist/components/api.min.js
tastypie_api_doc/static/tastypie_api_doc/bower_components/semantic/dist/components/breadcrumb.css
tastypie_api_doc/static/tastypie_api_doc/bower_components/semantic/dist/components/breadcrumb.min.css
tastypie_api_doc/static/tastypie_api_doc/bower_components/semantic/dist/components/button.css
