Metadata-Version: 1.1
Name: django-tastypie-simple-api-doc
Version: 0.5.0b1
Summary: A Django app to generate a simple and automatic api documentation with Tastypie
Home-page: https://github.com/matheuscas/django-tastypie-simple-api-doc
Author: Matheus Cardoso
Author-email: matheus.mcas@gmail.com
License: MIT
Keywords: django tastypie api documentation automatic
Platform: UNKNOWN
Classifier: Development Status :: 4 - Beta
Classifier: Intended Audience :: Developers
Classifier: Topic :: Software Development :: Libraries :: Python Modules
Classifier: Topic :: System :: Systems Administration :: Authentication/Directory
Classifier: Environment :: Web Environment
Classifier: Framework :: Django
Classifier: Framework :: Django :: 1.8
Classifier: License :: OSI Approved :: MIT License
Classifier: Operating System :: OS Independent
Classifier: Programming Language :: Python :: 2
Classifier: Programming Language :: Python :: 2.6
Classifier: Programming Language :: Python :: 2.7
Classifier: Topic :: Internet :: WWW/HTTP
Classifier: Topic :: Internet :: WWW/HTTP :: Dynamic Content
